Workbook

Sheet RA Information
A2: SECURITY & BUSINESS RISK ASSESSMENT — INDIAN OCEAN PIRACY OPERATIONS
A4: RISK MANAGEMENT INFORMATION
A6: Risk Assessment ID: | B6: SM RA-004-IOR-001 | C6: Location: | D6: Indian Ocean Region — Somali Basin, Gulf of Aden, Arabian Sea
A7: Activity Description: | B7: Security and business risk assessment for armed anti-piracy operations (PCASP deployment) protecting commercial vessels transiting the Indian Ocean Region, including embarkation/disembarkation, transit security, and piracy defence operations.
A8: Applicable Standards: | B8: ISO 18788:2015, ISO 28007:2015, ISO 28000:2022, ISO 9001:2015, ISO 45001:2018 | C8: BMP Reference: | D8: BMP-MS (Best Management Practices to Deter Piracy and Enhance Maritime Security)
A9: Assessment Date: | B9: 23 March 2026 | C9: Risk Owner: | D9: Group Compliance Director
A10: Assessed By: | B10: Darren Watts — Group Compliance Director | C10: Next Review: | D10: 23 June 2026 (or following significant threat change)
A11: Classification: | B11: CONFIDENTIAL — INTERNAL USE ONLY | C11: Applicable Entities: | D11: Seagull Maritime Ltd (Malta), Seagull Maritime FZCo (UAE)
A12: Threat Sources: | B12: IMB Annual Report 2025, UKMTO, MSCHOA, EU NAVFOR ATALANTA, Dryad Global, Skuld, BMP-MS, Palaemon Maritime
A13: Responsible Persons: | B13: Senior Operations Manager, Group Compliance Director, Client Representative
B14: Senior Management have responsibility for approving armed anti-piracy operations based on the security and business risk profile. All risks rated High or Critical must be explicitly acknowledged before operations proceed.
B15: The Project Team must ensure all security, legal, commercial, and operational risks are understood and appropriate controls are in place before PCASP deployment. This includes compliance with BMP-MS, flag state requirements, and regional licensing.
B16: The Client is respectfully requested to review this assessment and provide any vessel-specific, route-specific, or operational information that may affect the risk profile.
A19: COMMUNICATION & CONSULTATION / RECORDING & REPORTING / MONITORING & REVIEW
A20: This security and business risk assessment must be reviewed by Senior Management prior to commencement of operations. Findings must be communicated to all relevant personnel including Operations, Commercial, and PCASP team leaders. Any changes to the threat environment must trigger an immediate re-assessment.
A21: Monitoring: The risk profile must be reviewed if circumstances change materially — including changes to piracy threat levels (UKMTO/IMB advisories), flag state licensing requirements, insurance conditions, BMP-MS updates, or client operational requirements. Minimum review frequency: quarterly or following any significant incident.
A22: This assessment is complementary to SM RA-003 (Health & Safety Risk Assessment) and must be read in conjunction with applicable SOPs (SMS/SOP/IO series), the company SMS, and current BMP-MS/MISTO guidance.
A23: SCOPE & CONTEXT
A24: Seagull Maritime provides armed Private Contracted Armed Security Personnel (PCASP) for anti-piracy protection on commercial vessels transiting the Indian Ocean Region (IOR), including the Somali Basin, Gulf of Aden, Arabian Sea, and associated high-risk areas. Operations involve 3-4 man armed security teams deployed from floating armouries (OPL Galle, Grey Palm, Golden Palm, Moroni) to protect vessels against piracy, armed robbery, and hijack attempts. This assessment covers the full spectrum of security, political, economic, social, technological, legal, and environmental risks associated with these operations, including the resurgence of Somali piracy activity since October 2025.

Sheet Methodology
A2: RISK ASSESSMENT METHODOLOGY
B4: Probability Rating x Consequence Rating = Risk Rating
B6: PROBABILITY
B7: Likelihood | C7: Description | E7: Previous Occurrences | F7: Description
B8: 1 | C8: Cannot occur / not applicable | E8: 1 | F8: Has never occurred
B9: 2 | C9: Unlikely to occur | E9: 2 | F9: Has occurred once in similar ops
B10: 3 | C10: Could occur at some point | E10: 3 | F10: Has occurred more than once
B11: 4 | C11: Likely to occur | E11: 4 | F11: Has occurred frequently
B12: 5 | C12: Almost certain to occur | E12: 5 | F12: Common/expected occurrence
B15: CONSEQUENCE (6 Sub-Categories Averaged)
A16: Rating | B16: Loss of Client/Contract | C16: Inability to Meet Requirements | D16: Risk to Human Health | E16: Violation of Regulations | F16: Company Reputation | G16: Financial Impact
A17: 1 | B17: No impact | C17: No impact | D17: No injury | E17: No breach | F17: No impact | G17: Negligible cost
A18: 2 | B18: Minor dissatisfaction | C18: Minor delay | D18: First aid injury | E18: Minor non-compliance | F18: Local negative comment | G18: <$10,000
A19: 3 | B19: Formal complaint | C19: Partial failure | D19: Medical treatment | E19: Regulatory warning | F19: Industry-level negative | G19: $10,000-$100,000
A20: 4 | B20: Contract at risk | C20: Major failure | D20: Serious injury/hospitalisation | E20: Formal investigation | F20: Media coverage | G20: $100,000-$1,000,000
A21: 5 | B21: Contract terminated | C21: Total failure | D21: Death or permanent disability | E21: Criminal prosecution | F21: International media/boycott | G21: >$1,000,000
B24: RISK RATING MATRIX (Probability × Consequence Average)
B25: Probability ↓ / Consequence → | C25: 1 | D25: 2 | E25: 3 | F25: 4 | G25: 5
B26: 1 | C26: 1 | D26: 2 | E26: 3 | F26: 4 | G26: 5
B27: 2 | C27: 2 | D27: 4 | E27: 6 | F27: 8 | G27: 10
B28: 3 | C28: 3 | D28: 6 | E28: 9 | F28: 12 | G28: 15
B29: 4 | C29: 4 | D29: 8 | E29: 12 | F29: 16 | G29: 20
B30: 5 | C30: 5 | D30: 10 | E30: 15 | F30: 20 | G30: 25
B32: RISK LEVELS
B33: Low (1-4) | D33: Acceptable. Monitor and review.
B34: Moderate (5-12) | D34: Requires documented controls. Review regularly.
B35: High (13-16) | D35: Significant risk. Senior management approval required.
B36: Critical (17-25) | D36: Unacceptable. TERMINATE or redesign operation.

Sheet Risk Assessment
A2: SECURITY & BUSINESS RISK ASSESSMENT
E3: PROBABILITY | H3: CONSEQUENCE | O3: PRE-RISK | S3: POST-RISK
A4: Ref | B4: Risk Category | C4: Risk / Threat Description | D4: Affected Processes | E4: Likelihood (1-5) | F4: Prev. Occurrences (1-5) | G4: Prob. Rating | H4: Loss of Client/ Contract | I4: Inability to Meet Job Requirements | J4: Risk to Human Health | K4: Violation of Regulations | L4: Company Reputation | M4: Cost of Correction/ Financial | N4: Cons. Rating | O4: Pre-Risk Rating | P4: Risk Level | Q4: Risk Treatment | R4: Control Measures (Mitigation Plan) | S4: Post-Prob. Rating | T4: Post-Cons. Rating | U4: Post-Risk Rating | V4: Risk Level | W4: Responsibility | X4: Status
A5: SEC-001 | B5: POLITICAL | C5: Somali piracy resurgence since October 2025. PAGs operating 300-800nm offshore using hijacked dhows as motherships. HELLAS APHRODITE hijacked Nov 2025 (560nm SE of Eyl). Up to 19 dhows hijacked since Nov 2025. Houthi-pirate technology transfer confirmed (advanced GPS, weapons). EU NAVFOR ATALANTA capacity stretched by Red Sea/Iran crisis diversion. | D5: Operations Security | E5: 5 | F5: 5 | G5: =AVERAGE(E5,F5) -> 5 | H5: 5 | I5: 5 | J5: 5 | K5: 4 | L5: 5 | M5: 5 | N5: =AVERAGE(H5:M5) -> 4.8333333 | O5: =G5*N5 -> 24.166667 | P5: =IF(O5>=17,"Critical",IF(O5>=13,"High",IF(O5>=5,"Moderate","Low"))) -> Critical | Q5: TREAT | R5: Mandatory BMP-MS compliance on all transits (speed >15kts where possible, enhanced watch routines, razor wire, water spray). Daily intelligence updates from Dryad Global/UKMTO/MSCHOA before and during transit. Minimum 4-man PCASP team with appropriately scaled weapons fit. Transit planning to avoid known PAG operating areas — route via IRTC where applicable. Pre-deployment intelligence briefing to PCASP TL covering current PAG TTPs, mothership descriptions, and known operating areas. Vessel hardening inspection per SM SOP Annex C before entering HRA. Citadel plan confirmed and tested with Master before transit. | S5: 4 | T5: 3.5 | U5: =IF(AND(S5<>"[PROJECT TEAM]",T5<>"[PROJECT TEAM]"),S5*T5,"") -> 14 | V5: =IF(U5="","",IF(U5>=17,"Critical",IF(U5>=13,"High",IF(U5>=5,"Moderate","Low")))) -> High | W5: Operations Manager / PCASP TL | X5: Open
A6: SEC-002 | B6: POLITICAL | C6: Geopolitical instability in the Horn of Africa. Al-Shabaab influence on Somali coastal regions, Houthi-pirate nexus confirmed, and weakened Somali/Puntland maritime enforcement. PMPF capability reduced. Risk of pirate groups obtaining more sophisticated weaponry and intelligence from Houthi collaboration. | D6: Operations Intelligence | E6: 4 | F6: 4 | G6: =AVERAGE(E6,F6) -> 4 | H6: 4 | I6: 4 | J6: 4 | K6: 3 | L6: 4 | M6: 3 | N6: =AVERAGE(H6:M6) -> 3.6666667 | O6: =G6*N6 -> 14.666667 | P6: =IF(O6>=17,"Critical",IF(O6>=13,"High",IF(O6>=5,"Moderate","Low"))) -> High | Q6: TREAT | R6: Intelligence subscription maintained (Dryad Global, Ambrey, PVI). Weekly threat assessment updates distributed to Ops team and PCASP TLs. Liaison with EU NAVFOR ATALANTA and CMF for naval patrol schedules and escort availability. Escalation protocol: if intelligence indicates Houthi-pirate collaboration in specific area, reroute or delay transit. Regional security network maintained through SAMI membership and industry contacts. | S6: 3 | T6: 3 | U6: =IF(AND(S6<>"[PROJECT TEAM]",T6<>"[PROJECT TEAM]"),S6*T6,"") -> 9 | V6: =IF(U6="","",IF(U6>=17,"Critical",IF(U6>=13,"High",IF(U6>=5,"Moderate","Low")))) -> Moderate | W6: Group Compliance Director / Intelligence | X6: Open
A7: SEC-003 | B7: POLITICAL | C7: Iran-US conflict (active since 28 Feb 2026) impacting wider Indian Ocean security posture. Naval assets redeployed from anti-piracy to conflict operations. Strait of Hormuz effectively closed. Gulf of Aden corridor security degraded. Houthi Red Sea attacks paused but "fingers on trigger" — could resume at any time, further degrading IOR transit safety. | D7: Operations Planning | E7: 4 | F7: 4 | G7: =AVERAGE(E7,F7) -> 4 | H7: 4 | I7: 5 | J7: 4 | K7: 3 | L7: 4 | M7: 4 | N7: =AVERAGE(H7:M7) -> 4 | O7: =G7*N7 -> 16 | P7: =IF(O7>=17,"Critical",IF(O7>=13,"High",IF(O7>=5,"Moderate","Low"))) -> High | Q7: TREAT | R7: Ongoing monitoring of Iran-US conflict and impact on IOR naval presence. Contingency routing plans for Gulf of Aden disruption (alternative embark/disembark ports). Client communication protocol for threat level changes affecting transit timelines. War risk insurance reviewed and updated quarterly. If Houthi attacks resume in Red Sea, immediate review of all active transits and suspension of non-essential movements. | S7: 3 | T7: 3.5 | U7: =IF(AND(S7<>"[PROJECT TEAM]",T7<>"[PROJECT TEAM]"),S7*T7,"") -> 10.5 | V7: =IF(U7="","",IF(U7>=17,"Critical",IF(U7>=13,"High",IF(U7>=5,"Moderate","Low")))) -> Moderate | W7: Group Compliance Director / CCO | X7: Open
A8: SEC-004 | B8: ECONOMIC | C8: War risk insurance premiums spiking across IOR. Joint War Committee listed areas expanding. Client cost sensitivity increasing. Some clients deferring transits or rerouting via Cape of Good Hope, reducing demand for IOR PCASP services. Revenue impact from reduced transit volumes. | D8: Business Dev Finance | E8: 4 | F8: 4 | G8: =AVERAGE(E8,F8) -> 4 | H8: 4 | I8: 3 | J8: 1 | K8: 2 | L8: 3 | M8: 5 | N8: =AVERAGE(H8:M8) -> 3 | O8: =G8*N8 -> 12 | P8: =IF(O8>=17,"Critical",IF(O8>=13,"High",IF(O8>=5,"Moderate","Low"))) -> Moderate | Q8: TREAT | R8: Diversified client base — not dependent on single shipping lane or client. Flexible PCASP deployment model to scale down costs during low-demand periods. Insurance costs monitored quarterly and passed through to clients where contractually permissible. Alternative revenue streams maintained (WAF, consultancy, Seagull Offshore). Financial forecasting model updated monthly reflecting transit volume trends. | S8: 3 | T8: 2.5 | U8: =IF(AND(S8<>"[PROJECT TEAM]",T8<>"[PROJECT TEAM]"),S8*T8,"") -> 7.5 | V8: =IF(U8="","",IF(U8>=17,"Critical",IF(U8>=13,"High",IF(U8>=5,"Moderate","Low")))) -> Moderate | W8: CCO / Finance | X8: Open
A9: SEC-005 | B9: ECONOMIC | C9: Contractual exposure from piracy incidents during transit. Client vessels attacked or boarded while under Seagull protection could trigger contractual liability, reputational damage, and insurance claims. GUARDCON limitations and exclusions need clear communication. | D9: Business Dev Legal | E9: 3 | F9: 3 | G9: =AVERAGE(E9,F9) -> 3 | H9: 5 | I9: 4 | J9: 3 | K9: 4 | L9: 5 | M9: 5 | N9: =AVERAGE(H9:M9) -> 4.3333333 | O9: =G9*N9 -> 13 | P9: =IF(O9>=17,"Critical",IF(O9>=13,"High",IF(O9>=5,"Moderate","Low"))) -> High | Q9: TRANSFER / TREAT | R9: GUARDCON contract terms clearly define liability limitations and exclusions. Professional Indemnity and Public Liability insurance maintained at levels appropriate to contract values. Pre-transit Risk Assessment completed and signed off before every deployment. Post-incident legal response protocol established with Tatham Law (retained legal advisors). Incident documentation procedure per SM SOP Annex F — evidence preservation from first contact. Client briefing on shared responsibility model during pre-transit engagement. | S9: 2 | T9: 3.5 | U9: =IF(AND(S9<>"[PROJECT TEAM]",T9<>"[PROJECT TEAM]"),S9*T9,"") -> 7 | V9: =IF(U9="","",IF(U9>=17,"Critical",IF(U9>=13,"High",IF(U9>=5,"Moderate","Low")))) -> Moderate | W9: Group Compliance Director / Legal | X9: Open
A10: SEC-006 | B10: SOCIAL | C10: PCASP welfare and fatigue during extended embarkations. Monsoon season (Jun-Sep SW, Oct-Dec NE) restricts operations and extends deployment times. Remote operating environment with limited communication, medical support, and shore leave. Mental health and wellbeing risks for deployed personnel. | D10: HR Operations | E10: 4 | F10: 4 | G10: =AVERAGE(E10,F10) -> 4 | H10: 2 | I10: 3 | J10: 4 | K10: 3 | L10: 3 | M10: 2 | N10: =AVERAGE(H10:M10) -> 2.8333333 | O10: =G10*N10 -> 11.333333 | P10: =IF(O10>=17,"Critical",IF(O10>=13,"High",IF(O10>=5,"Moderate","Low"))) -> Moderate | Q10: TREAT | R10: Maximum embarkation duration policy (28 days unless exceptional circumstances approved by Ops Director). Welfare check-in protocol — PCASP TL reports crew welfare status daily to Ops. Satellite phone/email access for personal communications. Mental health awareness included in pre-deployment briefing. Rotation planning to avoid back-to-back deployments without minimum rest period (14 days). Monsoon season operational restrictions documented in SM SOP — no personnel transfers in sea state >4. | S10: 3 | T10: 2.5 | U10: =IF(AND(S10<>"[PROJECT TEAM]",T10<>"[PROJECT TEAM]"),S10*T10,"") -> 7.5 | V10: =IF(U10="","",IF(U10>=17,"Critical",IF(U10>=13,"High",IF(U10>=5,"Moderate","Low")))) -> Moderate | W10: Operations Manager / HR | X10: Open
A11: SEC-007 | B11: SOCIAL | C11: Right to Life — use of force during piracy defence. PCASP may need to use lethal force to defend vessel and crew. Proportionality, rules for use of force (RUF), and escalation of force procedures must be strictly followed. Risk of disproportionate response, collateral damage to fishermen, or post-incident legal action. ISO 18788 Clause 6.1.1 human rights due diligence. | D11: Operations Legal Compliance | E11: 3 | F11: 2 | G11: =AVERAGE(E11,F11) -> 2.5 | H11: 5 | I11: 5 | J11: 5 | K11: 5 | L11: 5 | M11: 5 | N11: =AVERAGE(H11:M11) -> 5 | O11: =G11*N11 -> 12.5 | P11: =IF(O11>=17,"Critical",IF(O11>=13,"High",IF(O11>=5,"Moderate","Low"))) -> Moderate | Q11: TREAT | R11: Rules for Use of Force (RUF) trained, briefed, and signed by all PCASP before every deployment. Graduated response procedure: visual warning → audible warning → warning shots → disabling fire → aimed fire (last resort). Only TL-authorised escalation beyond warning shots. All use of force incidents reported immediately to Ops and Compliance per SM SOP Annex E. Post-incident debrief and evidence preservation (CCTV, logs, witness statements). Annual RUF refresher training mandatory. Fisherman identification training — recognition of legitimate fishing vessels vs. PAG skiffs. | S11: 2 | T11: 3.5 | U11: =IF(AND(S11<>"[PROJECT TEAM]",T11<>"[PROJECT TEAM]"),S11*T11,"") -> 7 | V11: =IF(U11="","",IF(U11>=17,"Critical",IF(U11>=13,"High",IF(U11>=5,"Moderate","Low")))) -> Moderate | W11: Group Compliance Director / PCASP TL | X11: Open
A12: SEC-008 | B12: SOCIAL | C12: Freedom from Inhumane Treatment — captured or detained PCASP. If vessel boarded and PCASP detained by pirates, risk of hostage-taking, physical harm, and prolonged captivity. No guaranteed rescue capability. Historical precedent of years-long captivity in Somalia. | D12: Operations HR | E12: 2 | F12: 2 | G12: =AVERAGE(E12,F12) -> 2 | H12: 5 | I12: 5 | J12: 5 | K12: 4 | L12: 5 | M12: 5 | N12: =AVERAGE(H12:M12) -> 4.8333333 | O12: =G12*N12 -> 9.6666667 | P12: =IF(O12>=17,"Critical",IF(O12>=13,"High",IF(O12>=5,"Moderate","Low"))) -> Moderate | Q12: TREAT | R12: Citadel procedures tested and briefed with Master and crew before entering HRA. SSAS activation protocol confirmed. Communication of vessel position to UKMTO/MSCHOA at all times in HRA. If boarded, PCASP trained in hostage survival procedures (resistance is not required — life preservation priority). K&R insurance maintained. Crisis management plan in place with designated crisis management team. Family liaison officer designated in crisis plan. Post-incident psychological support contracted. | S12: 2 | T12: 3.5 | U12: =IF(AND(S12<>"[PROJECT TEAM]",T12<>"[PROJECT TEAM]"),S12*T12,"") -> 7 | V12: =IF(U12="","",IF(U12>=17,"Critical",IF(U12>=13,"High",IF(U12>=5,"Moderate","Low")))) -> Moderate | W12: Operations Manager / CEO | X12: Open
A13: SEC-009 | B13: TECHNOLOGICAL | C13: Pirate technology escalation. Confirmed Houthi technology transfer to Somali PAGs — advanced GPS/satellite devices and weapons. Pirates now capable of tracking vessel movements and coordinating multi-skiff attacks at extended range. Traditional BMP-MS measures (speed, freeboard, razor wire) less effective against technologically enhanced attacks. | D13: Operations Intelligence | E13: 4 | F13: 3 | G13: =AVERAGE(E13,F13) -> 3.5 | H13: 4 | I13: 4 | J13: 4 | K13: 3 | L13: 4 | M13: 4 | N13: =AVERAGE(H13:M13) -> 3.8333333 | O13: =G13*N13 -> 13.416667 | P13: =IF(O13>=17,"Critical",IF(O13>=13,"High",IF(O13>=5,"Moderate","Low"))) -> High | Q13: TREAT | R13: Intelligence updates specifically monitoring pirate technology developments. Counter-surveillance awareness in pre-deployment briefs — AIS management, EMCON procedures where appropriate. Enhanced lookout procedures using thermal imaging and radar watch in addition to visual. PCASP weapon capability scaled to counter enhanced pirate armament — minimum rifle-calibre weapons. Regular review of BMP-MS effectiveness against evolving threat — additional hardening measures where BMP-MS baseline insufficient. | S13: 3 | T13: 3 | U13: =IF(AND(S13<>"[PROJECT TEAM]",T13<>"[PROJECT TEAM]"),S13*T13,"") -> 9 | V13: =IF(U13="","",IF(U13>=17,"Critical",IF(U13>=13,"High",IF(U13>=5,"Moderate","Low")))) -> Moderate | W13: Operations Manager / Intelligence | X13: Open
A14: SEC-010 | B14: TECHNOLOGICAL | C14: Communication and tracking limitations in remote IOR operating areas. Satellite phone and AIS coverage gaps. Delayed reporting to UKMTO/MSCHOA during incidents. VBA coordination challenges when operating 600+ nm offshore. | D14: Operations Safety | E14: 3 | F14: 3 | G14: =AVERAGE(E14,F14) -> 3 | H14: 3 | I14: 4 | J14: 3 | K14: 3 | L14: 3 | M14: 3 | N14: =AVERAGE(H14:M14) -> 3.1666667 | O14: =G14*N14 -> 9.5 | P14: =IF(O14>=17,"Critical",IF(O14>=13,"High",IF(O14>=5,"Moderate","Low"))) -> Moderate | Q14: TREAT | R14: Dual satellite communication systems on all transits (primary + backup). Mandatory UKMTO registration and regular position reporting schedule (every 4 hours in HRA). VBA coordination protocol with defined communication windows and contingency for comms failure. Pre-deployment comms check with all equipment tested and confirmed operational. Spare sat phone batteries and charging equipment in PCASP deployment kit. | S14: 2 | T14: 2.5 | U14: =IF(AND(S14<>"[PROJECT TEAM]",T14<>"[PROJECT TEAM]"),S14*T14,"") -> 5 | V14: =IF(U14="","",IF(U14>=17,"Critical",IF(U14>=13,"High",IF(U14>=5,"Moderate","Low")))) -> Moderate | W14: Operations Manager / PCASP TL | X14: Open
A15: SEC-011 | B15: LEGAL | C15: Multi-jurisdictional weapons licensing and carriage. Flag state authorisations required (UK, Liberia, Panama, Palau, Guinea-Bissau). Transit through territorial waters of multiple states. Each jurisdiction has different requirements for weapons carriage, storage, and use. Licence renewal and compliance monitoring across multiple flag states. | D15: Compliance Operations | E15: 3 | F15: 3 | G15: =AVERAGE(E15,F15) -> 3 | H15: 4 | I15: 4 | J15: 2 | K15: 5 | L15: 4 | M15: 4 | N15: =AVERAGE(H15:M15) -> 3.8333333 | O15: =G15*N15 -> 11.5 | P15: =IF(O15>=17,"Critical",IF(O15>=13,"High",IF(O15>=5,"Moderate","Low"))) -> Moderate | Q15: TREAT | R15: Weapons licence tracker maintained by Compliance — all flag state authorisations logged with expiry dates and renewal triggers (90 days before expiry). Territorial water transit planning — route to avoid jurisdictions where weapons carriage is prohibited or unclear. SM PRO document control procedure ensures current licence copies held onboard and at head office. New flag state applications initiated immediately when client confirms vessel flag. Legal review of any new jurisdiction before first transit. | S15: 2 | T15: 3 | U15: =IF(AND(S15<>"[PROJECT TEAM]",T15<>"[PROJECT TEAM]"),S15*T15,"") -> 6 | V15: =IF(U15="","",IF(U15>=17,"Critical",IF(U15>=13,"High",IF(U15>=5,"Moderate","Low")))) -> Moderate | W15: Group Compliance Director | X15: Open
A16: SEC-012 | B16: LEGAL | C16: Post-incident legal exposure from use of force. If PCASP discharges weapons, multiple jurisdictions may claim authority (flag state, coastal state, PCASP nationality state). Risk of criminal prosecution, civil liability, and regulatory investigation. Need for immediate legal response capability and evidence preservation protocols. | D16: Legal Compliance | E16: 3 | F16: 2 | G16: =AVERAGE(E16,F16) -> 2.5 | H16: 5 | I16: 4 | J16: 3 | K16: 5 | L16: 5 | M16: 5 | N16: =AVERAGE(H16:M16) -> 4.5 | O16: =G16*N16 -> 11.25 | P16: =IF(O16>=17,"Critical",IF(O16>=13,"High",IF(O16>=5,"Moderate","Low"))) -> Moderate | Q16: TREAT | R16: Tatham Law retained for immediate legal advice following any use of force incident. Evidence preservation protocol: CCTV footage secured, bridge logs copied, PCASP individual statements taken within 2 hours, TL incident report within 6 hours. PCASP legal expenses insurance confirmed before deployment. Flag state notification protocol documented. Post-incident communication plan — no external statements without legal review. Annual tabletop exercise simulating post-UoF legal response. | S16: 2 | T16: 3.5 | U16: =IF(AND(S16<>"[PROJECT TEAM]",T16<>"[PROJECT TEAM]"),S16*T16,"") -> 7 | V16: =IF(U16="","",IF(U16>=17,"Critical",IF(U16>=13,"High",IF(U16>=5,"Moderate","Low")))) -> Moderate | W16: Group Compliance Director / Legal | X16: Open
... A24: SEC-020 | B24: POLITICAL | C24: Client due diligence and vetting requirements increasing. CSOs and major oil companies (Shell, ExxonMobil, Vitol) demanding higher standards of documentation, compliance evidence, and operational transparency. Failure to meet DD standards results in deselection. Seagull must maintain audit-ready DD packs at all times. | D24: Compliance Business Dev | E24: 4 | F24: 4 | G24: =AVERAGE(E24,F24) -> 4 | H24: 5 | I24: 3 | J24: 1 | K24: 3 | L24: 4 | M24: 3 | N24: =AVERAGE(H24:M24) -> 3.1666667 | O24: =G24*N24 -> 12.666667 | P24: =IF(O24>=17,"Critical",IF(O24>=13,"High",IF(O24>=5,"Moderate","Low"))) -> Moderate | Q24: TREAT | R24: DD packs updated quarterly and after any significant document change. OCIMF master form maintained as single source of truth (ref ocimf_master_answers.json). Navigation guide (SM-DD-NAV-IOR-2025) updated when folder structure changes. Pre-DD submission review by Compliance — no pack goes to client without GCD sign-off. Gap register maintained and actively closed. Client feedback post-DD incorporated into continuous improvement. | S24: 3 | T24: 2.5 | U24: =IF(AND(S24<>"[PROJECT TEAM]",T24<>"[PROJECT TEAM]"),S24*T24,"") -> 7.5 | V24: =IF(U24="","",IF(U24>=17,"Critical",IF(U24>=13,"High",IF(U24>=5,"Moderate","Low")))) -> Moderate | W24: Group Compliance Director / CCO | X24: Open

Sheet Risk Dashboard
A2: RISK DASHBOARD
B4: KEY METRICS
B5: Total Risks | D5: Critical | F5: High | H5: Moderate
B6: =COUNTA('Risk Assessment'!A5:A24) -> 20 | D6: =COUNTIF('Risk Assessment'!P5:P24,"Critical") -> 1 | F6: =COUNTIF('Risk Assessment'!P5:P24,"High") -> 4 | H6: =COUNTIF('Risk Assessment'!P5:P24,"Moderate") -> 15
B8: Avg. Pre-Risk Rating | D8: Highest Pre-Risk Rating | F8: Low Risk Count
B9: =AVERAGE('Risk Assessment'!O5:O24) -> 12.158333 | D9: =MAX('Risk Assessment'!O5:O24) -> 24.166667 | F9: =COUNTIF('Risk Assessment'!P5:P24,"Low") -> 0
B11: PRE-RISK OUTLOOK
B12: Critical (17-25) | E12: =COUNTIF('Risk Assessment'!P5:P24,"Critical") -> 1
B13: High (13-16) | E13: =COUNTIF('Risk Assessment'!P5:P24,"High") -> 4
B14: Moderate (5-12) | E14: =COUNTIF('Risk Assessment'!P5:P24,"Moderate") -> 15
B15: Low (1-4) | E15: =COUNTIF('Risk Assessment'!P5:P24,"Low") -> 0
B17: RISK DISTRIBUTION BY PESTLE CATEGORY
B18: Category | C18: Count | D18: Avg Rating | E18: Highest
B19: POLITICAL | C19: =COUNTIF('Risk Assessment'!B5:B24,"POLITICAL") -> 4 | D19: =IFERROR(AVERAGEIF('Risk Assessment'!B5:B24,"POLITICAL",'Risk Assessment'!O5:O24),0) -> 16.875 | E19: =IFERROR(_xludf.aggregate(14,6,'Risk Assessment'!O5:O24/('Risk Assessment'!B5:B24="POLITICAL"),1),0) -> 0
B20: ECONOMIC | C20: =COUNTIF('Risk Assessment'!B5:B24,"ECONOMIC") -> 3 | D20: =IFERROR(AVERAGEIF('Risk Assessment'!B5:B24,"ECONOMIC",'Risk Assessment'!O5:O24),0) -> 12.555556 | E20: =IFERROR(_xludf.aggregate(14,6,'Risk Assessment'!O5:O24/('Risk Assessment'!B5:B24="ECONOMIC"),1),0) -> 0
B21: SOCIAL | C21: =COUNTIF('Risk Assessment'!B5:B24,"SOCIAL") -> 4 | D21: =IFERROR(AVERAGEIF('Risk Assessment'!B5:B24,"SOCIAL",'Risk Assessment'!O5:O24),0) -> 9.875 | E21: =IFERROR(_xludf.aggregate(14,6,'Risk Assessment'!O5:O24/('Risk Assessment'!B5:B24="SOCIAL"),1),0) -> 0
B22: TECHNOLOGICAL | C22: =COUNTIF('Risk Assessment'!B5:B24,"TECHNOLOGICAL") -> 3 | D22: =IFERROR(AVERAGEIF('Risk Assessment'!B5:B24,"TECHNOLOGICAL",'Risk Assessment'!O5:O24),0) -> 10.972222 | E22: =IFERROR(_xludf.aggregate(14,6,'Risk Assessment'!O5:O24/('Risk Assessment'!B5:B24="TECHNOLOGICAL"),1),0) -> 0
B23: LEGAL | C23: =COUNTIF('Risk Assessment'!B5:B24,"LEGAL") -> 4 | D23: =IFERROR(AVERAGEIF('Risk Assessment'!B5:B24,"LEGAL",'Risk Assessment'!O5:O24),0) -> 10.479167 | E23: =IFERROR(_xludf.aggregate(14,6,'Risk Assessment'!O5:O24/('Risk Assessment'!B5:B24="LEGAL"),1),0) -> 0
B24: ENVIRONMENTAL | C24: =COUNTIF('Risk Assessment'!B5:B24,"ENVIRONMENTAL") -> 2 | D24: =IFERROR(AVERAGEIF('Risk Assessment'!B5:B24,"ENVIRONMENTAL",'Risk Assessment'!O5:O24),0) -> 11.833333 | E24: =IFERROR(_xludf.aggregate(14,6,'Risk Assessment'!O5:O24/('Risk Assessment'!B5:B24="ENVIRONMENTAL"),1),0) -> 0
