Workbook

Sheet RA Information
A2: SECURITY & BUSINESS RISK ASSESSMENT — GULF OF GUINEA OPERATIONS
A4: RISK MANAGEMENT INFORMATION
A6: Risk Assessment ID: | B6: SM RA-004-WAF-001 | C6: Location: | D6: Gulf of Guinea — Nigerian EEZ, Bight of Bonny, Gulf of Benin, wider GOG
A7: Activity Description: | B7: Security and business risk assessment for Security Escort Vessel (SEV) operations, local naval team activities, and vessel guarding/escort services in the Gulf of Guinea region, with focus on Nigerian territorial and EEZ waters.
A8: Applicable Standards: | B8: ISO 18788:2015, ISO 28007:2015, ISO 28000:2022, ISO 9001:2015, ISO 45001:2018 | C8: Regulatory Framework: | D8: NIMASA, SPOMO Act, Nigeria Navy MOU, ISPS Code
A9: Assessment Date: | B9: 23 March 2026 | C9: Risk Owner: | D9: Group Compliance Director
A10: Assessed By: | B10: Darren Watts — Group Compliance Director | C10: Next Review: | D10: 23 June 2026 (or following significant threat change)
A11: Classification: | B11: CONFIDENTIAL — INTERNAL USE ONLY | C11: Applicable Entities: | D11: Seagull Maritime Ltd (Malta), Seagull Logistics and Maritime Services Ltd (Nigeria), Seagull Maritime Hellas (Greece)
A12: Threat Sources: | B12: IMB Annual Report 2025, MARAD 2025-008, MDAT-GoG, Dryad Global, NIMASA, Atlantic Council GOG Assessment
A13: Responsible Persons: | B13: WAF Operations Director, Senior Operations Manager, Group Compliance Director, Client Representative
B14: Senior Management have responsibility for approving SEV and naval team operations based on the security and business risk profile. All risks rated High or Critical must be explicitly acknowledged before operations proceed.
B15: The Project Team must ensure all security, legal, commercial, and operational risks are understood and appropriate controls are in place before team deployment. This includes compliance with Nigerian Navy MOU requirements, NIMASA regulations, and local licensing.
B16: The Client is respectfully requested to review this assessment and provide any vessel-specific, operational, or location-specific information that may affect the risk profile.
A19: COMMUNICATION & CONSULTATION / RECORDING & REPORTING / MONITORING & REVIEW
A20: This security and business risk assessment must be reviewed by Senior Management prior to commencement of operations. Findings must be communicated to all relevant personnel including Operations, Commercial, WAF Operations Director, and team leaders. Any changes to the threat environment must trigger an immediate re-assessment.
A21: Monitoring: The risk profile must be reviewed if circumstances change materially — including changes to GOG threat levels, Nigerian Navy MOU status, NIMASA regulatory requirements, insurance conditions, or client operational requirements. Minimum review frequency: quarterly or following any significant incident.
A22: This assessment is complementary to SM RA-003 (Health & Safety Risk Assessment) and must be read in conjunction with applicable SOPs (SMS/SOP/WAF series), the company SMS, and current BMP-MS/MISTO guidance for West Africa.
A23: SCOPE & CONTEXT
A24: Seagull Maritime provides armed security teams for vessel protection in the Gulf of Guinea (GOG) and wider West African (WAF) maritime area. Operations include Ship Escort Vessel (SEV) deployment and locally sourced Nigerian Navy team coordination for protection against piracy, armed robbery, kidnap for ransom (KFR), and maritime crime. This assessment covers the full spectrum of security, political, economic, social, technological, legal, and environmental risks associated with these operations, including the complex regulatory environment in Nigeria, the ongoing threat of Niger Delta-linked maritime crime, and the commercial challenges of operating in a competitive market alongside the Nigerian Navy Deep Blue Project.

Sheet Methodology
A2: RISK ASSESSMENT METHODOLOGY
B4: Probability Rating x Consequence Rating = Risk Rating
B6: PROBABILITY
B7: Likelihood | C7: Description | E7: Previous Occurrences | F7: Description
B8: 1 | C8: Cannot occur / not applicable | E8: 1 | F8: Has never occurred
B9: 2 | C9: Unlikely to occur | E9: 2 | F9: Has occurred once in similar ops
B10: 3 | C10: Could occur at some point | E10: 3 | F10: Has occurred more than once
B11: 4 | C11: Likely to occur | E11: 4 | F11: Has occurred frequently
B12: 5 | C12: Almost certain to occur | E12: 5 | F12: Common/expected occurrence
B15: CONSEQUENCE (6 Sub-Categories Averaged)
A16: Rating | B16: Loss of Client/Contract | C16: Inability to Meet Requirements | D16: Risk to Human Health | E16: Violation of Regulations | F16: Company Reputation | G16: Financial Impact
A17: 1 | B17: No impact | C17: No impact | D17: No injury | E17: No breach | F17: No impact | G17: Negligible cost
A18: 2 | B18: Minor dissatisfaction | C18: Minor delay | D18: First aid injury | E18: Minor non-compliance | F18: Local negative comment | G18: <$10,000
A19: 3 | B19: Formal complaint | C19: Partial failure | D19: Medical treatment | E19: Regulatory warning | F19: Industry-level negative | G19: $10,000-$100,000
A20: 4 | B20: Contract at risk | C20: Major failure | D20: Serious injury/hospitalisation | E20: Formal investigation | F20: Media coverage | G20: $100,000-$1,000,000
A21: 5 | B21: Contract terminated | C21: Total failure | D21: Death or permanent disability | E21: Criminal prosecution | F21: International media/boycott | G21: >$1,000,000
B24: RISK RATING MATRIX (Probability × Consequence Average)
B25: Probability ↓ / Consequence → | C25: 1 | D25: 2 | E25: 3 | F25: 4 | G25: 5
B26: 1 | C26: 1 | D26: 2 | E26: 3 | F26: 4 | G26: 5
B27: 2 | C27: 2 | D27: 4 | E27: 6 | F27: 8 | G27: 10
B28: 3 | C28: 3 | D28: 6 | E28: 9 | F28: 12 | G28: 15
B29: 4 | C29: 4 | D29: 8 | E29: 12 | F29: 16 | G29: 20
B30: 5 | C30: 5 | D30: 10 | E30: 15 | F30: 20 | G30: 25
B32: RISK LEVELS
B33: Low (1-4) | D33: Acceptable. Monitor and review.
B34: Moderate (5-12) | D34: Requires documented controls. Review regularly.
B35: High (13-16) | D35: Significant risk. Senior management approval required.
B36: Critical (17-25) | D36: Unacceptable. TERMINATE or redesign operation.

Sheet Risk Assessment
A2: SECURITY & BUSINESS RISK ASSESSMENT
E3: PROBABILITY | H3: CONSEQUENCE | O3: PRE-RISK | S3: POST-RISK
A4: Ref | B4: Risk Category | C4: Risk / Threat Description | D4: Affected Processes | E4: Likelihood (1-5) | F4: Prev. Occurrences (1-5) | G4: Prob. Rating | H4: Loss of Client/ Contract | I4: Inability to Meet Job Requirements | J4: Risk to Human Health | K4: Violation of Regulations | L4: Company Reputation | M4: Cost of Correction/ Financial | N4: Cons. Rating | O4: Pre-Risk Rating | P4: Risk Level | Q4: Risk Treatment | R4: Control Measures (Mitigation Plan) | S4: Post-Prob. Rating | T4: Post-Cons. Rating | U4: Post-Risk Rating | V4: Risk Level | W4: Responsibility | X4: Status
A5: SEC-001 | B5: POLITICAL | C5: Political instability in Nigeria and wider Gulf of Guinea. Changing government policies toward maritime security, potential shifts in NIMASA/Nigeria Navy cooperation. Inconsistent enforcement of maritime regulations across coastal states (Nigeria, Benin, Cameroon, Ghana, Togo). Military coup risk in region (recent history in West Africa). | D5: Operations Business Dev | E5: 4 | F5: 4 | G5: =AVERAGE(E5,F5) | H5: 4 | I5: 4 | J5: 3 | K5: 3 | L5: 4 | M5: 4 | N5: =AVERAGE(H5:M5) | O5: =G5*N5 | P5: =IF(O5>=17,"Critical",IF(O5>=13,"High",IF(O5>=5,"Moderate","Low"))) | Q5: TREAT | R5: Ongoing monitoring of political developments across GOG coastal states (Nigeria, Benin, Cameroon, Ghana). Country risk assessments reviewed quarterly. In-country representation through Seagull Nigeria (Lagos) and Seagull Hellas (Greece) provides local intelligence. Christoforos Antzoulatos (WAF Ops Director) maintains government and military relationships on the ground. Contingency plans for political disruption — alternative operational bases identified. Client contracts include force majeure clauses covering political instability. | S5: 3 | T5: 3 | U5: =IF(AND(S5<>"[PROJECT TEAM]",T5<>"[PROJECT TEAM]"),S5*T5,"") | V5: =IF(U5="","",IF(U5>=17,"Critical",IF(U5>=13,"High",IF(U5>=5,"Moderate","Low")))) | W5: WAF Operations Director / GCD | X5: Open
A6: SEC-002 | B6: POLITICAL | C6: Nigeria Navy MOU dependency. Seagull operations in Nigerian waters require active MOU with Nigeria Navy. MOU renewal, compliance, and relationship management are critical. Navy personnel quality and reliability varies. Risk of MOU termination or non-renewal disrupting all WAF operations. | D6: Operations Legal | E6: 3 | F6: 3 | G6: =AVERAGE(E6,F6) | H6: 5 | I6: 5 | J6: 2 | K6: 4 | L6: 4 | M6: 5 | N6: =AVERAGE(H6:M6) | O6: =G6*N6 | P6: =IF(O6>=17,"Critical",IF(O6>=13,"High",IF(O6>=5,"Moderate","Low"))) | Q6: TREAT | R6: Nigeria Navy MOU managed as a critical relationship — regular engagement meetings with Navy command. MOU renewal tracked with 6-month lead time — Compliance flags renewal at 180 days before expiry. Relationship not dependent on single point of contact — multiple Navy liaison officers engaged. MOU compliance documented and evidenced continuously — ready for Navy review at any time. Alternative security delivery model explored as contingency (private armed security where legally permissible). MOU terms reviewed annually by legal advisors to ensure current regulatory alignment. | S6: 2 | T6: 3.5 | U6: =IF(AND(S6<>"[PROJECT TEAM]",T6<>"[PROJECT TEAM]"),S6*T6,"") | V6: =IF(U6="","",IF(U6>=17,"Critical",IF(U6>=13,"High",IF(U6>=5,"Moderate","Low")))) | W6: WAF Operations Director / CEO | X6: Open
A7: SEC-003 | B7: POLITICAL | C7: Niger Delta militancy and kidnapping for ransom (KFR). KFR groups target senior crew members and Western/foreign personnel. 23 crew kidnapped across 4 incidents in GOG in 2025. 8 passengers abducted in Ikang Waterways (Dec 2025). KFR gangs operate from Niger Delta with sophisticated intelligence networks. | D7: Operations Security HR | E7: 4 | F7: 5 | G7: =AVERAGE(E7,F7) | H7: 5 | I7: 5 | J7: 5 | K7: 4 | L7: 5 | M7: 5 | N7: =AVERAGE(H7:M7) | O7: =G7*N7 | P7: =IF(O7>=17,"Critical",IF(O7>=13,"High",IF(O7>=5,"Moderate","Low"))) | Q7: TREAT | R7: Mandatory pre-transit intelligence assessment covering Niger Delta militancy and KFR threat for specific operating area. Enhanced watch routines on all SEVs — minimum 2 lookouts during darkness/restricted visibility. Foreign/senior crew personnel movements restricted in high-risk port areas — shore leave policy enforced. K&R insurance maintained with adequate cover levels reviewed annually. Crisis management plan in place with designated CMT — tested annually via tabletop exercise. Anti-KFR training included in all WAF deployment briefs — recognition, avoidance, and survival if taken. Vessel lighting and security watch procedures per SM SOP at anchor and in port. | S7: 3 | T7: 3.5 | U7: =IF(AND(S7<>"[PROJECT TEAM]",T7<>"[PROJECT TEAM]"),S7*T7,"") | V7: =IF(U7="","",IF(U7>=17,"Critical",IF(U7>=13,"High",IF(U7>=5,"Moderate","Low")))) | W7: WAF Operations Director / PCASP TL | X7: Open
A8: SEC-004 | B8: ECONOMIC | C8: SEV charter and operating cost exposure. Time-chartered vessels (A30, Elijah, Eltee 1, Holy Shield 1, Mediator, Titran) represent significant fixed costs. Client contract delays, cancellations, or payment defaults leave Seagull exposed. Fuel price volatility. Currency fluctuation (Naira instability). | D8: Finance Operations | E8: 4 | F8: 4 | G8: =AVERAGE(E8,F8) | H8: 4 | I8: 3 | J8: 1 | K8: 2 | L8: 3 | M8: 5 | N8: =AVERAGE(H8:M8) | O8: =G8*N8 | P8: =IF(O8>=17,"Critical",IF(O8>=13,"High",IF(O8>=5,"Moderate","Low"))) | Q8: TREAT | R8: SEV charter costs managed through long-term time charter agreements with defined notice periods. Client contract terms require minimum commitment periods to cover fixed vessel costs. Financial exposure monitored monthly — charter costs vs revenue by vessel. Fuel hedging or pass-through clauses in client contracts where possible. Currency exposure managed — USD-denominated contracts preferred. Naira exposure minimised. Vessel utilisation tracked — underperforming vessels flagged for redeployment or release. | S8: 3 | T8: 3 | U8: =IF(AND(S8<>"[PROJECT TEAM]",T8<>"[PROJECT TEAM]"),S8*T8,"") | V8: =IF(U8="","",IF(U8>=17,"Critical",IF(U8>=13,"High",IF(U8>=5,"Moderate","Low")))) | W8: CCO / Finance | X8: Open
A9: SEC-005 | B9: ECONOMIC | C9: Oil price dependency. GOG maritime security demand directly linked to oil and gas operations. Low oil prices reduce E&P activity, reducing demand for escort and guarding services. Client budget cuts cascade to PMSC contract values and volumes. | D9: Business Dev Finance | E9: 3 | F9: 4 | G9: =AVERAGE(E9,F9) | H9: 4 | I9: 3 | J9: 1 | K9: 1 | L9: 3 | M9: 4 | N9: =AVERAGE(H9:M9) | O9: =G9*N9 | P9: =IF(O9>=17,"Critical",IF(O9>=13,"High",IF(O9>=5,"Moderate","Low"))) | Q9: TREAT | R9: Client base diversified across oil majors, traders, and independents — not dependent on single client. Service diversification — escort, guarding, consultancy, vessel provision — reduces single-service dependency. Market intelligence monitored — E&P activity levels, rig counts, cargo volumes tracked quarterly. Flexible cost model — ability to scale down operations if market contracts. Seagull Offshore development provides alternative revenue stream independent of oil price. | S9: 3 | T9: 2.5 | U9: =IF(AND(S9<>"[PROJECT TEAM]",T9<>"[PROJECT TEAM]"),S9*T9,"") | V9: =IF(U9="","",IF(U9>=17,"Critical",IF(U9>=13,"High",IF(U9>=5,"Moderate","Low")))) | W9: CCO / CEO | X9: Open
A10: SEC-006 | B10: ECONOMIC | C10: Insurance and P&I exposure for SEV operations. Hull and machinery insurance for chartered vessels. War risk and K&R insurance premiums. P&I cover for crew and third-party liability. GOG insurance costs rising due to persistent KFR threat. Entity alignment (UK vs Malta) for insurance — recently resolved per Shell finding. | D10: Finance Compliance | E10: 3 | F10: 3 | G10: =AVERAGE(E10,F10) | H10: 3 | I10: 3 | J10: 2 | K10: 4 | L10: 3 | M10: 4 | N10: =AVERAGE(H10:M10) | O10: =G10*N10 | P10: =IF(O10>=17,"Critical",IF(O10>=13,"High",IF(O10>=5,"Moderate","Low"))) | Q10: TRANSFER / TREAT | R10: Hull & machinery, P&I, and war risk insurance maintained across all chartered vessels. K&R insurance in place for all deployed personnel. Insurance broker annual review of cover adequacy against operational risk profile. Insurance entity alignment confirmed (Malta entity — Shell Finding #4 COMPLETED). Claims management procedure documented — prompt notification and evidence preservation. Insurance certificates current and available in DD folder. | S10: 2 | T10: 2.5 | U10: =IF(AND(S10<>"[PROJECT TEAM]",T10<>"[PROJECT TEAM]"),S10*T10,"") | V10: =IF(U10="","",IF(U10>=17,"Critical",IF(U10>=13,"High",IF(U10>=5,"Moderate","Low")))) | W10: Finance / GCD | X10: Open
A11: SEC-007 | B11: SOCIAL | C11: Right to Life — armed confrontation during escort or guarding operations. Nigerian naval team or Seagull security personnel may need to use lethal force. Rules of engagement defined by Nigeria Navy MOU. Proportionality and escalation of force under ISO 18788 Clause 6.1.1. Risk of civilian casualties in congested Nigerian waters. | D11: Operations Legal Compliance | E11: 3 | F11: 3 | G11: =AVERAGE(E11,F11) | H11: 5 | I11: 5 | J11: 5 | K11: 5 | L11: 5 | M11: 5 | N11: =AVERAGE(H11:M11) | O11: =G11*N11 | P11: =IF(O11>=17,"Critical",IF(O11>=13,"High",IF(O11>=5,"Moderate","Low"))) | Q11: TREAT | R11: Rules of Engagement (ROE) governed by Nigeria Navy MOU — Seagull personnel operate within Navy-defined parameters. Clear legal separation: weapons handled by Navy personnel only under MOU terms. Seagull observers document all security incidents — independent evidence trail. Graduated response procedures briefed to all onboard personnel. ISO 18788 Clause 6.1.1 human rights due diligence applied — proportionality is non-negotiable. Post-incident reporting within 2 hours to Ops and Compliance. Annual use of force training/refresher for all Seagull WAF personnel. | S11: 2 | T11: 3.5 | U11: =IF(AND(S11<>"[PROJECT TEAM]",T11<>"[PROJECT TEAM]"),S11*T11,"") | V11: =IF(U11="","",IF(U11>=17,"Critical",IF(U11>=13,"High",IF(U11>=5,"Moderate","Low")))) | W11: WAF Operations Director / GCD | X11: Open
A12: SEC-008 | B12: SOCIAL | C12: Freedom from Inhumane Treatment — kidnapped crew or security personnel. If SEV or client vessel boarded, crew and guards face KFR captivity. Historical precedent of weeks to months in captivity in Niger Delta. Physical abuse, deprivation, psychological trauma during captivity. No guaranteed rescue — ransom typically the only resolution. | D12: Operations HR Security | E12: 3 | F12: 4 | G12: =AVERAGE(E12,F12) | H12: 5 | I12: 5 | J12: 5 | K12: 4 | L12: 5 | M12: 5 | N12: =AVERAGE(H12:M12) | O12: =G12*N12 | P12: =IF(O12>=17,"Critical",IF(O12>=13,"High",IF(O12>=5,"Moderate","Low"))) | Q12: TREAT | R12: K&R insurance with specialist response provider (Specialist crisis consultancy retained). Crisis management plan tested annually — roles, communications, family liaison defined. Anti-KFR SOPs — vessel hardening, citadel/safe room on SEVs, SSAS activation protocol. Personnel tracking — all deployed staff positions known and reported daily. No ransom payment policy communicated — but crisis response prioritises life preservation. Post-incident psychological support contracted for all affected personnel and families. | S12: 2 | T12: 3.5 | U12: =IF(AND(S12<>"[PROJECT TEAM]",T12<>"[PROJECT TEAM]"),S12*T12,"") | V12: =IF(U12="","",IF(U12>=17,"Critical",IF(U12>=13,"High",IF(U12>=5,"Moderate","Low")))) | W12: CEO / WAF Operations Director | X12: Open
A13: SEC-009 | B13: SOCIAL | C13: Local naval team welfare and performance. Nigeria Navy personnel assigned under MOU may have variable training, discipline, and reliability. Cultural and language barriers. Fatigue from extended deployments. Risk of unauthorised actions by naval personnel reflecting on Seagull. Need for continuous monitoring and reporting. | D13: Operations HR | E13: 4 | F13: 4 | G13: =AVERAGE(E13,F13) | H13: 3 | I13: 4 | J13: 3 | K13: 3 | L13: 4 | M13: 2 | N13: =AVERAGE(H13:M13) | O13: =G13*N13 | P13: =IF(O13>=17,"Critical",IF(O13>=13,"High",IF(O13>=5,"Moderate","Low"))) | Q13: TREAT | R13: Navy personnel performance monitored by Seagull vessel master and TL — issues reported immediately. Regular feedback to Navy command on personnel quality — positive and negative. Cultural awareness training for Seagull international crew working alongside Nigerian Navy. Welfare provisions for Navy personnel onboard — meals, accommodation, rest periods per MOU. Clear command structure defined in MOU — vessel master retains overall authority for navigation and safety. Rotation requests submitted to Navy when individual performance is unsatisfactory. | S13: 3 | T13: 2.5 | U13: =IF(AND(S13<>"[PROJECT TEAM]",T13<>"[PROJECT TEAM]"),S13*T13,"") | V13: =IF(U13="","",IF(U13>=17,"Critical",IF(U13>=13,"High",IF(U13>=5,"Moderate","Low")))) | W13: WAF Operations Director / Vessel Master | X13: Open
A14: SEC-010 | B14: SOCIAL | C14: Non-discrimination and labour rights for local and deployed personnel. Fair treatment of Nigerian crew, naval liaison, and subcontracted staff. ISO 18788 Clause 6.1.1 human rights requirements. Risk of exploitation allegations or labour disputes undermining compliance standing. | D14: HR Compliance | E14: 2 | F14: 2 | G14: =AVERAGE(E14,F14) | H14: 3 | I14: 2 | J14: 2 | K14: 4 | L14: 4 | M14: 3 | N14: =AVERAGE(H14:M14) | O14: =G14*N14 | P14: =IF(O14>=17,"Critical",IF(O14>=13,"High",IF(O14>=5,"Moderate","Low"))) | Q14: TREAT | R14: SM POL Equal Opportunities Policy applies to all personnel regardless of engagement type. Local employment terms reviewed by legal to ensure compliance with Nigerian labour law. Grievance procedure accessible to all staff including subcontracted and Navy personnel. Whistleblowing procedure per SM POL — confidential reporting channel available. Annual training module on human rights and non-discrimination per ISO 18788. | S14: 2 | T14: 2 | U14: =IF(AND(S14<>"[PROJECT TEAM]",T14<>"[PROJECT TEAM]"),S14*T14,"") | V14: =IF(U14="","",IF(U14>=17,"Critical",IF(U14>=13,"High",IF(U14>=5,"Moderate","Low")))) | W14: HR / GCD | X14: Open
A15: SEC-011 | B15: TECHNOLOGICAL | C15: SEV maintenance and seaworthiness. Chartered vessels operating in tropical waters subject to corrosion, mechanical degradation, and age-related failures. Critical spares availability (ref: SM RA-SEV MED4 001 - Critical Spares Risk Assessment). Drydocking schedules vs operational commitments. Class society compliance. | D15: Operations Safety | E15: 4 | F15: 4 | G15: =AVERAGE(E15,F15) | H15: 4 | I15: 5 | J15: 4 | K15: 4 | L15: 4 | M15: 4 | N15: =AVERAGE(H15:M15) | O15: =G15*N15 | P15: =IF(O15>=17,"Critical",IF(O15>=13,"High",IF(O15>=5,"Moderate","Low"))) | Q15: TREAT | R15: Planned maintenance system (PMS) implemented on all SEVs — maintained by vessel engineering team. Critical spares risk assessment completed (ref SM RA-SEV MED4 001) — minimum stock levels defined and monitored. Drydocking schedule planned 12 months ahead — coordinated with operational commitments. Class society surveys tracked and completed on time — no overdue conditions of class. Vessel condition reports submitted monthly by vessel master — defects tracked to closure. Charter party terms include maintenance obligations and minimum vessel standards. | S15: 3 | T15: 3 | U15: =IF(AND(S15<>"[PROJECT TEAM]",T15<>"[PROJECT TEAM]"),S15*T15,"") | V15: =IF(U15="","",IF(U15>=17,"Critical",IF(U15>=13,"High",IF(U15>=5,"Moderate","Low")))) | W15: WAF Operations Director / Vessel Master | X15: Open
A16: SEC-012 | B16: TECHNOLOGICAL | C16: Communication and tracking in GOG operating areas. AIS manipulation/spoofing by pirate groups. VHF/HF radio reliability. Satellite communication costs for fleet. Real-time tracking of multiple vessels across wide operating area. Coordination between SEVs, client vessels, and Nigeria Navy. | D16: Operations Safety | E16: 3 | F16: 3 | G16: =AVERAGE(E16,F16) | H16: 3 | I16: 4 | J16: 3 | K16: 3 | L16: 3 | M16: 3 | N16: =AVERAGE(H16:M16) | O16: =G16*N16 | P16: =IF(O16>=17,"Critical",IF(O16>=13,"High",IF(O16>=5,"Moderate","Low"))) | Q16: TREAT | R16: Dual communication systems on all SEVs (VHF + satellite). AIS monitoring at Seagull operations centre — any AIS anomalies flagged immediately. Fleet tracking system with geo-fencing alerts for operating area boundaries. Communication schedule defined — vessels report position and status minimum every 4 hours. Contingency protocol for comms failure — pre-defined rally points and escalation to Navy/MDAT-GoG. | S16: 2 | T16: 2.5 | U16: =IF(AND(S16<>"[PROJECT TEAM]",T16<>"[PROJECT TEAM]"),S16*T16,"") | V16: =IF(U16="","",IF(U16>=17,"Critical",IF(U16>=13,"High",IF(U16>=5,"Moderate","Low")))) | W16: Operations Manager / Vessel Master | X16: Open
... A24: SEC-020 | B24: ECONOMIC | C24: Competitor and market dynamics in GOG. Local Nigerian security companies with lower cost base. International PMSCs competing for same contracts. Deep Blue Project and improved Navy capability could reduce client demand for private maritime security. Market consolidation pressure. | D24: Business Dev Finance | E24: 4 | F24: 4 | G24: =AVERAGE(E24,F24) | H24: 4 | I24: 3 | J24: 1 | K24: 2 | L24: 3 | M24: 4 | N24: =AVERAGE(H24:M24) | O24: =G24*N24 | P24: =IF(O24>=17,"Critical",IF(O24>=13,"High",IF(O24>=5,"Moderate","Low"))) | Q24: TREAT | R24: Value-based competitive positioning — ISO certifications, Shell approval, ICoCA membership as differentiators. Client retention focus — regular client engagement meetings, feedback loops, service improvement. Market intelligence on Deep Blue Project development — monitor for impact on private security demand. Local partnership model through Seagull Nigeria — cost advantage over purely international competitors. Tender response quality maintained — Compliance review of all tenders before submission. Diversification into adjacent services (vessel provision, consultancy) reduces dependency on escort/guarding market. | S24: 3 | T24: 2.5 | U24: =IF(AND(S24<>"[PROJECT TEAM]",T24<>"[PROJECT TEAM]"),S24*T24,"") | V24: =IF(U24="","",IF(U24>=17,"Critical",IF(U24>=13,"High",IF(U24>=5,"Moderate","Low")))) | W24: CCO / CEO | X24: Open

Sheet Risk Dashboard
A2: RISK DASHBOARD
B4: KEY METRICS
B5: Total Risks | D5: Critical | F5: High | H5: Moderate
B6: =COUNTA('Risk Assessment'!A5:A24) | D6: =COUNTIF('Risk Assessment'!P5:P24,"Critical") | F6: =COUNTIF('Risk Assessment'!P5:P24,"High") | H6: =COUNTIF('Risk Assessment'!P5:P24,"Moderate")
B8: Avg. Pre-Risk Rating | D8: Highest Pre-Risk Rating | F8: Low Risk Count
B9: =AVERAGE('Risk Assessment'!O5:O24) | D9: =MAX('Risk Assessment'!O5:O24) | F9: =COUNTIF('Risk Assessment'!P5:P24,"Low")
B11: PRE-RISK OUTLOOK
B12: Critical (17-25) | E12: =COUNTIF('Risk Assessment'!P5:P24,"Critical")
B13: High (13-16) | E13: =COUNTIF('Risk Assessment'!P5:P24,"High")
B14: Moderate (5-12) | E14: =COUNTIF('Risk Assessment'!P5:P24,"Moderate")
B15: Low (1-4) | E15: =COUNTIF('Risk Assessment'!P5:P24,"Low")
B17: RISK DISTRIBUTION BY PESTLE CATEGORY
B18: Category | C18: Count | D18: Avg Rating | E18: Highest
B19: POLITICAL | C19: =COUNTIF('Risk Assessment'!B5:B24,"POLITICAL") | D19: =IFERROR(AVERAGEIF('Risk Assessment'!B5:B24,"POLITICAL",'Risk Assessment'!O5:O24),0) | E19: =IFERROR(aggregate(14,6,'Risk Assessment'!O5:O24/('Risk Assessment'!B5:B24="POLITICAL"),1),0)
B20: ECONOMIC | C20: =COUNTIF('Risk Assessment'!B5:B24,"ECONOMIC") | D20: =IFERROR(AVERAGEIF('Risk Assessment'!B5:B24,"ECONOMIC",'Risk Assessment'!O5:O24),0) | E20: =IFERROR(aggregate(14,6,'Risk Assessment'!O5:O24/('Risk Assessment'!B5:B24="ECONOMIC"),1),0)
B21: SOCIAL | C21: =COUNTIF('Risk Assessment'!B5:B24,"SOCIAL") | D21: =IFERROR(AVERAGEIF('Risk Assessment'!B5:B24,"SOCIAL",'Risk Assessment'!O5:O24),0) | E21: =IFERROR(aggregate(14,6,'Risk Assessment'!O5:O24/('Risk Assessment'!B5:B24="SOCIAL"),1),0)
B22: TECHNOLOGICAL | C22: =COUNTIF('Risk Assessment'!B5:B24,"TECHNOLOGICAL") | D22: =IFERROR(AVERAGEIF('Risk Assessment'!B5:B24,"TECHNOLOGICAL",'Risk Assessment'!O5:O24),0) | E22: =IFERROR(aggregate(14,6,'Risk Assessment'!O5:O24/('Risk Assessment'!B5:B24="TECHNOLOGICAL"),1),0)
B23: LEGAL | C23: =COUNTIF('Risk Assessment'!B5:B24,"LEGAL") | D23: =IFERROR(AVERAGEIF('Risk Assessment'!B5:B24,"LEGAL",'Risk Assessment'!O5:O24),0) | E23: =IFERROR(aggregate(14,6,'Risk Assessment'!O5:O24/('Risk Assessment'!B5:B24="LEGAL"),1),0)
B24: ENVIRONMENTAL | C24: =COUNTIF('Risk Assessment'!B5:B24,"ENVIRONMENTAL") | D24: =IFERROR(AVERAGEIF('Risk Assessment'!B5:B24,"ENVIRONMENTAL",'Risk Assessment'!O5:O24),0) | E24: =IFERROR(aggregate(14,6,'Risk Assessment'!O5:O24/('Risk Assessment'!B5:B24="ENVIRONMENTAL"),1),0)
